plasmatk/__init__.py
plasmatk/cpp/a.cpp
plasmatk/cpp/a.txt
plasmatk/cpp/b.cpp
plasmatk/parameters.py
plasmatk/plotting.py
plasmatk-0.6.0.dist-info/LICENSE
plasmatk-0.6.0.dist-info/METADATA
plasmatk-0.6.0.dist-info/WHEEL
plasmatk-0.6.0.dist-info/RECORD
