Metadata-Version: 2.1
Name: plasmatk
Version: 0.6.0
Summary: A collection of tools for plasma physicists
License: MIT
Author: Ryan Park
Requires-Python: >=3.9,<4.0
Classifier: License :: OSI Approved :: MIT License
Classifier: Programming Language :: Python :: 3
Classifier: Programming Language :: Python :: 3.9
Classifier: Programming Language :: Python :: 3.10
Classifier: Programming Language :: Python :: 3.11
Classifier: Programming Language :: Python :: 3.12
Requires-Dist: matplotlib (>=3.8.1,<4.0.0)
Requires-Dist: numpy (>=1.26.1,<2.0.0) ; python_version >= "3.9" and python_version < "3.13"
Requires-Dist: pandas (>=2.1.2,<3.0.0)
Requires-Dist: scipy (>=1.11.3,<2.0.0) ; python_version >= "3.9" and python_version < "3.13"
